LICENSE
MANIFEST.in
README.rst
setup.py
django_envi.egg-info/PKG-INFO
django_envi.egg-info/SOURCES.txt
django_envi.egg-info/dependency_links.txt
django_envi.egg-info/top_level.txt
envi/__init__.py
envi/conf.py
envi/constants.py
envi/middleware/__init__.py
envi/middleware/base.py
envi/middleware/footer.py
envi/templates/envi/footer.html