Metadata-Version: 1.0
Name: django-envi
Version: 0.2.1
Summary: Lightweight set of middleware classes that inject visual indicators for each type of environment that a project is deployed to.
Home-page: https://github.com/teapow/django-envi
Author: Thomas Power
Author-email: thomaspwr@gmail.com
License: BSD License
Platform: UNKNOWN
